tospotify/__init__.py
tospotify/__main__.py
tospotify/generator.py
tospotify/parser.py
tospotify/processing.py
tospotify/run.py
tospotify/search.py
tospotify/types/__init__.py
tospotify/types/artists.py
tospotify/types/queries.py
tospotify/types/titles.py
tospotify-0.3.4.dist-info/LICENSE
tospotify-0.3.4.dist-info/METADATA
tospotify-0.3.4.dist-info/WHEEL
tospotify-0.3.4.dist-info/entry_points.txt
tospotify-0.3.4.dist-info/top_level.txt
tospotify-0.3.4.dist-info/zip-safe
tospotify-0.3.4.dist-info/RECORD
