Metadata-Version: 2.1
Name: tospotify
Version: 0.3.4
Summary: Create/update a Spotify playlist from a local m3u playlist
Home-page: https://github.com/radujica/tospotify
Author: Radu Jica
Author-email: radu.jica+code@gmail.com
License: GPL-3.0
Classifier: Development Status :: 3 - Alpha
Classifier: License :: OSI Approved :: GNU General Public License v3 (GPLv3)
Classifier: Programming Language :: Python :: 3
Classifier: Programming Language :: Python :: 3.7
Classifier: Programming Language :: Python :: 3.8
Classifier: Programming Language :: Python :: 3.9
Classifier: Programming Language :: Python :: 3.10
Classifier: Programming Language :: Python :: 3.11
Classifier: Topic :: Multimedia :: Sound/Audio
Classifier: Operating System :: OS Independent
License-File: LICENSE
Requires-Dist: spotipy >=2.11.1
Requires-Dist: m3u8 <3.5,>=0.7.1
